geosun_transform/__init__.py
geosun_transform/py.typed
geosun_transform/v003geosunTransformLib.cp310-win_amd64.pyd
geosun_transform/v003geosunTransformLib.cp311-win_amd64.pyd
geosun_transform/v003geosunTransformLib.cp312-win_amd64.pyd
geosun_transform/v003geosunTransformLib.cp313-win_amd64.pyd
geosun_transform/v003geosunTransformLib.cp314-win_amd64.pyd
geosun_transform/v003geosunTransformLib.cp39-win_amd64.pyd
geosun_transform/v003geosunTransformLib.pyi
geosun_transform-0.0.3.dist-info/METADATA
geosun_transform-0.0.3.dist-info/WHEEL
geosun_transform-0.0.3.dist-info/top_level.txt
geosun_transform-0.0.3.dist-info/RECORD
